AUTHORS.rst
LICENSE
MANIFEST.in
README.md
requirements.txt
setup.cfg
setup.py
checkpython321/__init__.py
checkpython321/checkpython321.py
checkpython321/datainterface.py
checkpython321/fushion.py
checkpython321/integration.py
checkpython321/results.py
checkpython321.egg-info/PKG-INFO
checkpython321.egg-info/SOURCES.txt
checkpython321.egg-info/dependency_links.txt
checkpython321.egg-info/not-zip-safe
checkpython321.egg-info/requires.txt
checkpython321.egg-info/top_level.txt
tests/test_checkpython321.py