Metadata-Version: 2.1
Name: checkpython321
Version: 0.0.5
Summary: Python Boilerplate contains all the boilerplate you need to create a Python package.
Home-page: https://github.com/knop-k/checkpython321
Author: Krzysiek Knop
Author-email: knop.krzysiek@gmail.com
License: MIT license
Keywords: checkpython321
Classifier: Intended Audience :: Developers
Classifier: License :: OSI Approved :: MIT License
Classifier: Natural Language :: English
Classifier: Programming Language :: Python :: 3
Classifier: Programming Language :: Python :: 3.8
Classifier: Programming Language :: Python :: 3.9
Classifier: Programming Language :: Python :: 3.10
Classifier: Programming Language :: Python :: 3.11
Requires-Python: >=3.8
License-File: LICENSE
License-File: AUTHORS.rst
Requires-Dist: numpy==1.26.4
Requires-Dist: pandas==2.2.1
Requires-Dist: scipy==1.13.0
Requires-Dist: plotly==5.20.0
Requires-Dist: dash==2.16.1
